discourse2fedmsg_messages/__init__.py
discourse2fedmsg_messages-1.1.0.dist-info/LICENSE
discourse2fedmsg_messages-1.1.0.dist-info/METADATA
discourse2fedmsg_messages-1.1.0.dist-info/WHEEL
discourse2fedmsg_messages-1.1.0.dist-info/entry_points.txt
discourse2fedmsg_messages-1.1.0.dist-info/RECORD
